pynlple/__init__.py
pynlple/exceptions.py
pynlple/lime.py
pynlple/module.py
pynlple/utils.py
pynlple/data/__init__.py
pynlple/data/corpus.py
pynlple/data/datasource.py
pynlple/data/filesource.py
pynlple/data/jsonsource.py
pynlple/data/source.py
pynlple/ml/__init__.py
pynlple/ml/classifiers.py
pynlple/ml/transformers.py
pynlple/ml/vectorizers.py
pynlple/ml/supervised/__init__.py
pynlple/ml/supervised/feature_exploration.py
pynlple/ml/supervised/training.py
pynlple/processing/__init__.py
pynlple/processing/dictionary.py
pynlple/processing/emojis.py
pynlple/processing/mention.py
pynlple/processing/preprocessor.py
pynlple/processing/stopwords.py
pynlple/processing/text.py
pynlple/processing/token.py
pynlple/processing/data/currency.txt
pynlple/processing/data/punctuation.txt
pynlple/processing/data/special_symbols.txt
pynlple/processing/data/special_tags.txt
pynlple/processing/data/emoji/emoji_components.txt
pynlple/processing/data/emoji/emojis.txt
pynlple/processing/data/emoji/emojis_clustered.txt
pynlple/processing/data/rus/pos/conjunctions.txt
pynlple/processing/data/rus/pos/particles.txt
pynlple/processing/data/rus/pos/prepositions.txt
pynlple/processing/data/rus/pos/pronouns.txt
pynlple/processing/data/ukr/stopwords.txt
pyNlple-0.10.5.dist-info/METADATA
pyNlple-0.10.5.dist-info/WHEEL
pyNlple-0.10.5.dist-info/top_level.txt
pyNlple-0.10.5.dist-info/RECORD
