Metadata-Version: 2.2
Name: pyNlple
Version: 0.10.5
Summary: NLP procedures in python brought to you by YouScan.
Author-email: "YouScan Data Science team, NLP guild." <ds@youscan.io>
License: MIT Licence
Requires-Python: >=3.8
Requires-Dist: emoji>=0.5.0
Requires-Dist: numpy>=1.18
Requires-Dist: pandas>=0.19.0
Requires-Dist: requests>=2.20.0
Requires-Dist: scikit-learn>=0.22
Provides-Extra: es
Requires-Dist: elasticsearch~=8.17.0; extra == "es"
